rdflib_pyld_compat/__init__.py
rdflib_pyld_compat/convert.py
rdflib_pyld_compat-0.1.0.dist-info/METADATA
rdflib_pyld_compat-0.1.0.dist-info/WHEEL
rdflib_pyld_compat-0.1.0.dist-info/top_level.txt
rdflib_pyld_compat-0.1.0.dist-info/RECORD
