Metadata-Version: 2.1
Name: rdflib-pyld-compat
Version: 0.1.0
Summary: Conversion between rdflib and PyLD data formats for compatibility
Home-page: http://github.com/zimeon/rdflib-pyld-compat
Author: Simeon Warner
Author-email: simeon.warner@cornell.edu
License: UNKNOWN
Platform: UNKNOWN
Classifier: Development Status :: 4 - Beta
Classifier: Intended Audience :: Developers
Classifier: License :: OSI Approved :: Apache Software License
Classifier: Operating System :: OS Independent
Classifier: Programming Language :: Python
Classifier: Programming Language :: Python :: 3
Classifier: Programming Language :: Python :: 3.6
Classifier: Programming Language :: Python :: 3.7
Classifier: Programming Language :: Python :: 3.8
Classifier: Topic :: Software Development :: Libraries :: Python Modules
Requires-Dist: rdflib (>=4.2.0)
Requires-Dist: pyld
Requires-Dist: testfixtures
